datasponge/monitoring/__init__.py
datasponge/monitoring/monitoring.py
datasponge_monitoring-0.0.1.dist-info/METADATA
datasponge_monitoring-0.0.1.dist-info/WHEEL
datasponge_monitoring-0.0.1.dist-info/licenses/LICENSE
datasponge_monitoring-0.0.1.dist-info/RECORD
