Metadata-Version: 2.3
Name: datasponge-monitoring
Version: 0.0.1
Summary: A real-time data processing pipeline
Project-URL: Repository, https://github.com/innatelogic/datasponge-monitoring.git
Author-email: Benedikt Bollig <bollig@lmf.cnrs.fr>, Matthias Függer <mfuegger@lmf.cnrs.fr>, Thomas Nowak <thomas@thomasnowak.net>
Maintainer-email: Benedikt Bollig <bollig@lmf.cnrs.fr>, Matthias Függer <mfuegger@lmf.cnrs.fr>, Thomas Nowak <thomas@thomasnowak.net>
License: MIT License
License-File: LICENSE
Keywords: data processing,real-time,time series
Classifier: Development Status :: 4 - Beta
Classifier: Programming Language :: Python
Requires-Python: >=3.11
Requires-Dist: datasponge
